AgentBruno/__init__.py
AgentBruno/research.py
AgentBruno/storm.py
AgentBruno-0.0.5.dist-info/LICENSE
AgentBruno-0.0.5.dist-info/METADATA
AgentBruno-0.0.5.dist-info/WHEEL
AgentBruno-0.0.5.dist-info/entry_points.txt
AgentBruno-0.0.5.dist-info/top_level.txt
AgentBruno-0.0.5.dist-info/RECORD
