Metadata-Version: 2.1
Name: AgentBruno
Version: 0.0.5
Summary: Description of your package
Home-page: https://github.com/NinJagtap/AgentBruno.git
Author: Ninad Jagtap
Author-email: digitalforutility@gmail.com
Classifier: Programming Language :: Python :: 3
License-File: LICENSE
Requires-Dist: langchain ==0.1.14
Requires-Dist: langchain-community ==0.0.30
Requires-Dist: langchain-openai ==0.1.1
Requires-Dist: langgraph ==0.0.30
Requires-Dist: pinecone-client ==2.2.4
Requires-Dist: duckduckgo-search ==5.2.2
Requires-Dist: wikipedia ==1.4.0
Requires-Dist: scikit-learn ==1.4.1.post1
Requires-Dist: streamlit ==1.32.0
